src/__init__.py
src/sync.py
src/update_hook.py
colrev_sync-0.4.0.dist-info/METADATA
colrev_sync-0.4.0.dist-info/WHEEL
colrev_sync-0.4.0.dist-info/entry_points.txt
colrev_sync-0.4.0.dist-info/RECORD
