Metadata-Version: 2.4
Name: colrev-sync
Version: 0.4.0
Summary: CoLRev package for sync
Project-URL: repository, https://github.com/CoLRev-Environment/colrev-sync
Author-email: Gerit Wagner <gerit.wagner@uni-bamberg.de>
License: MIT
Requires-Python: <4,>=3.10
Requires-Dist: colrev>=0.13.2
